{
   "func (*File).Chdir() error": {
      "GeneratedClass": "",
      "GeneratedConditions": "",
      "Blocks": [
         {
            "Inp": [
               false,
               false
            ],
            "Outp": [
               false,
               false
            ]
         }
      ],
      "IsEnabled": false
   },
   "func (*File).Chmod(mode FileMode) error": {
      "GeneratedClass": "",
      "GeneratedConditions": "",
      "Blocks": [
         {
            "Inp": [
               false,
               false,
               false
            ],
            "Outp": [
               false,
               false,
               false
            ]
         }
      ],
      "IsEnabled": false
   },
   "func (*File).Chown(uid int, gid int) error": {
      "GeneratedClass": "",
      "GeneratedConditions": "",
      "Blocks": [
         {
            "Inp": [
               false,
               false,
               false,
               false
            ],
            "Outp": [
               false,
               false,
               false,
               false
            ]
         }
      ],
      "IsEnabled": false
   },
   "func (*File).Close() error": {
      "GeneratedClass": "",
      "GeneratedConditions": "",
      "Blocks": [
         {
            "Inp": [
               false,
               false
            ],
            "Outp": [
               false,
               false
            ]
         }
      ],
      "IsEnabled": false
   },
   "func (*File).Fd() uintptr": {
      "GeneratedClass": "\n    private class FileFd extends TaintTracking::FunctionModel, Method {\n      // signature: func (*File).Fd() uintptr\n      FileFd() { this.(Method).hasQualifiedName(\"os\", \"File\", \"Fd\") }\n\n      override predicate hasTaintFlow(FunctionInput inp, FunctionOutput outp) {\n        ((inp.isReceiver()) and (outp.isResult()))\n      }\n    }",
      "GeneratedConditions": "((inp.isReceiver()) and (outp.isResult()))",
      "Blocks": [
         {
            "Inp": [
               true,
               false
            ],
            "Outp": [
               false,
               true
            ]
         }
      ],
      "IsEnabled": true
   },
   "func (*File).Name() string": {
      "GeneratedClass": "",
      "GeneratedConditions": "",
      "Blocks": [
         {
            "Inp": [
               false,
               false
            ],
            "Outp": [
               false,
               false
            ]
         }
      ],
      "IsEnabled": false
   },
   "func (*File).Read(b []byte) (n int, err error)": {
      "GeneratedClass": "\n    private class FileRead extends TaintTracking::FunctionModel, Method {\n      // signature: func (*File).Read(b []byte) (n int, err error)\n      FileRead() { this.(Method).hasQualifiedName(\"os\", \"File\", \"Read\") }\n\n      override predicate hasTaintFlow(FunctionInput inp, FunctionOutput outp) {\n        ((inp.isReceiver()) and (outp.isParameter(0)))\n      }\n    }",
      "GeneratedConditions": "((inp.isReceiver()) and (outp.isParameter(0)))",
      "Blocks": [
         {
            "Inp": [
               true,
               false,
               false,
               false
            ],
            "Outp": [
               false,
               true,
               false,
               false
            ]
         }
      ],
      "IsEnabled": true
   },
   "func (*File).ReadAt(b []byte, off int64) (n int, err error)": {
      "GeneratedClass": "\n    private class FileReadAt extends TaintTracking::FunctionModel, Method {\n      // signature: func (*File).ReadAt(b []byte, off int64) (n int, err error)\n      FileReadAt() { this.(Method).hasQualifiedName(\"os\", \"File\", \"ReadAt\") }\n\n      override predicate hasTaintFlow(FunctionInput inp, FunctionOutput outp) {\n        ((inp.isReceiver()) and (outp.isParameter(0)))\n      }\n    }",
      "GeneratedConditions": "((inp.isReceiver()) and (outp.isParameter(0)))",
      "Blocks": [
         {
            "Inp": [
               true,
               false,
               false,
               false,
               false
            ],
            "Outp": [
               false,
               true,
               false,
               false,
               false
            ]
         }
      ],
      "IsEnabled": true
   },
   "func (*File).Readdir(n int) ([]FileInfo, error)": {
      "GeneratedClass": "",
      "GeneratedConditions": "",
      "Blocks": [
         {
            "Inp": [
               false,
               false,
               false,
               false
            ],
            "Outp": [
               false,
               false,
               false,
               false
            ]
         }
      ],
      "IsEnabled": false
   },
   "func (*File).Readdirnames(n int) (names []string, err error)": {
      "GeneratedClass": "",
      "GeneratedConditions": "",
      "Blocks": [
         {
            "Inp": [
               false,
               false,
               false,
               false
            ],
            "Outp": [
               false,
               false,
               false,
               false
            ]
         }
      ],
      "IsEnabled": false
   },
   "func (*File).Seek(offset int64, whence int) (ret int64, err error)": {
      "GeneratedClass": "",
      "GeneratedConditions": "",
      "Blocks": [
         {
            "Inp": [
               false,
               false,
               false,
               false,
               false
            ],
            "Outp": [
               false,
               false,
               false,
               false,
               false
            ]
         }
      ],
      "IsEnabled": false
   },
   "func (*File).SetDeadline(t time.Time) error": {
      "GeneratedClass": "",
      "GeneratedConditions": "",
      "Blocks": [
         {
            "Inp": [
               false,
               false,
               false
            ],
            "Outp": [
               false,
               false,
               false
            ]
         }
      ],
      "IsEnabled": false
   },
   "func (*File).SetReadDeadline(t time.Time) error": {
      "GeneratedClass": "",
      "GeneratedConditions": "",
      "Blocks": [
         {
            "Inp": [
               false,
               false,
               false
            ],
            "Outp": [
               false,
               false,
               false
            ]
         }
      ],
      "IsEnabled": false
   },
   "func (*File).SetWriteDeadline(t time.Time) error": {
      "GeneratedClass": "",
      "GeneratedConditions": "",
      "Blocks": [
         {
            "Inp": [
               false,
               false,
               false
            ],
            "Outp": [
               false,
               false,
               false
            ]
         }
      ],
      "IsEnabled": false
   },
   "func (*File).Stat() (FileInfo, error)": {
      "GeneratedClass": "",
      "GeneratedConditions": "",
      "Blocks": [
         {
            "Inp": [
               false,
               false,
               false
            ],
            "Outp": [
               false,
               false,
               false
            ]
         }
      ],
      "IsEnabled": false
   },
   "func (*File).Sync() error": {
      "GeneratedClass": "",
      "GeneratedConditions": "",
      "Blocks": [
         {
            "Inp": [
               false,
               false
            ],
            "Outp": [
               false,
               false
            ]
         }
      ],
      "IsEnabled": false
   },
   "func (*File).SyscallConn() (syscall.RawConn, error)": {
      "GeneratedClass": "\n    private class FileSyscallConn extends TaintTracking::FunctionModel, Method {\n      // signature: func (*File).SyscallConn() (syscall.RawConn, error)\n      FileSyscallConn() { this.(Method).hasQualifiedName(\"os\", \"File\", \"SyscallConn\") }\n\n      override predicate hasTaintFlow(FunctionInput inp, FunctionOutput outp) {\n        ((inp.isReceiver()) and (outp.isResult(0)))\n        or\n        ((inp.isResult(0)) and (outp.isReceiver()))\n      }\n    }",
      "GeneratedConditions": "((inp.isReceiver()) and (outp.isResult(0)))\n        or\n        ((inp.isResult(0)) and (outp.isReceiver()))",
      "Blocks": [
         {
            "Inp": [
               true,
               false,
               false
            ],
            "Outp": [
               false,
               true,
               false
            ]
         },
         {
            "Inp": [
               false,
               true,
               false
            ],
            "Outp": [
               true,
               false,
               false
            ]
         }
      ],
      "IsEnabled": true
   },
   "func (*File).Truncate(size int64) error": {
      "GeneratedClass": "",
      "GeneratedConditions": "",
      "Blocks": [
         {
            "Inp": [
               false,
               false,
               false
            ],
            "Outp": [
               false,
               false,
               false
            ]
         }
      ],
      "IsEnabled": false
   },
   "func (*File).Write(b []byte) (n int, err error)": {
      "GeneratedClass": "\n    private class FileWrite extends TaintTracking::FunctionModel, Method {\n      // signature: func (*File).Write(b []byte) (n int, err error)\n      FileWrite() { this.(Method).hasQualifiedName(\"os\", \"File\", \"Write\") }\n\n      override predicate hasTaintFlow(FunctionInput inp, FunctionOutput outp) {\n        ((inp.isParameter(0)) and (outp.isReceiver()))\n      }\n    }",
      "GeneratedConditions": "((inp.isParameter(0)) and (outp.isReceiver()))",
      "Blocks": [
         {
            "Inp": [
               false,
               true,
               false,
               false
            ],
            "Outp": [
               true,
               false,
               false,
               false
            ]
         }
      ],
      "IsEnabled": true
   },
   "func (*File).WriteAt(b []byte, off int64) (n int, err error)": {
      "GeneratedClass": "\n    private class FileWriteAt extends TaintTracking::FunctionModel, Method {\n      // signature: func (*File).WriteAt(b []byte, off int64) (n int, err error)\n      FileWriteAt() { this.(Method).hasQualifiedName(\"os\", \"File\", \"WriteAt\") }\n\n      override predicate hasTaintFlow(FunctionInput inp, FunctionOutput outp) {\n        ((inp.isParameter(0)) and (outp.isReceiver()))\n      }\n    }",
      "GeneratedConditions": "((inp.isParameter(0)) and (outp.isReceiver()))",
      "Blocks": [
         {
            "Inp": [
               false,
               true,
               false,
               false,
               false
            ],
            "Outp": [
               true,
               false,
               false,
               false,
               false
            ]
         }
      ],
      "IsEnabled": true
   },
   "func (*File).WriteString(s string) (n int, err error)": {
      "GeneratedClass": "\n    private class FileWriteString extends TaintTracking::FunctionModel, Method {\n      // signature: func (*File).WriteString(s string) (n int, err error)\n      FileWriteString() { this.(Method).hasQualifiedName(\"os\", \"File\", \"WriteString\") }\n\n      override predicate hasTaintFlow(FunctionInput inp, FunctionOutput outp) {\n        ((inp.isParameter(0)) and (outp.isReceiver()))\n      }\n    }",
      "GeneratedConditions": "((inp.isParameter(0)) and (outp.isReceiver()))",
      "Blocks": [
         {
            "Inp": [
               false,
               true,
               false,
               false
            ],
            "Outp": [
               true,
               false,
               false,
               false
            ]
         }
      ],
      "IsEnabled": true
   },
   "func (*LinkError).Error() string": {
      "GeneratedClass": "",
      "GeneratedConditions": "",
      "Blocks": [
         {
            "Inp": [
               false,
               false
            ],
            "Outp": [
               false,
               false
            ]
         }
      ],
      "IsEnabled": false
   },
   "func (*LinkError).Unwrap() error": {
      "GeneratedClass": "",
      "GeneratedConditions": "",
      "Blocks": [
         {
            "Inp": [
               false,
               false
            ],
            "Outp": [
               false,
               false
            ]
         }
      ],
      "IsEnabled": false
   },
   "func (*PathError).Error() string": {
      "GeneratedClass": "",
      "GeneratedConditions": "",
      "Blocks": [
         {
            "Inp": [
               false,
               false
            ],
            "Outp": [
               false,
               false
            ]
         }
      ],
      "IsEnabled": false
   },
   "func (*PathError).Timeout() bool": {
      "GeneratedClass": "",
      "GeneratedConditions": "",
      "Blocks": [
         {
            "Inp": [
               false,
               false
            ],
            "Outp": [
               false,
               false
            ]
         }
      ],
      "IsEnabled": false
   },
   "func (*PathError).Unwrap() error": {
      "GeneratedClass": "",
      "GeneratedConditions": "",
      "Blocks": [
         {
            "Inp": [
               false,
               false
            ],
            "Outp": [
               false,
               false
            ]
         }
      ],
      "IsEnabled": false
   },
   "func (*Process).Kill() error": {
      "GeneratedClass": "",
      "GeneratedConditions": "",
      "Blocks": [
         {
            "Inp": [
               false,
               false
            ],
            "Outp": [
               false,
               false
            ]
         }
      ],
      "IsEnabled": false
   },
   "func (*Process).Release() error": {
      "GeneratedClass": "",
      "GeneratedConditions": "",
      "Blocks": [
         {
            "Inp": [
               false,
               false
            ],
            "Outp": [
               false,
               false
            ]
         }
      ],
      "IsEnabled": false
   },
   "func (*Process).Signal(sig Signal) error": {
      "GeneratedClass": "",
      "GeneratedConditions": "",
      "Blocks": [
         {
            "Inp": [
               false,
               false,
               false
            ],
            "Outp": [
               false,
               false,
               false
            ]
         }
      ],
      "IsEnabled": false
   },
   "func (*Process).Wait() (*ProcessState, error)": {
      "GeneratedClass": "",
      "GeneratedConditions": "",
      "Blocks": [
         {
            "Inp": [
               false,
               false,
               false
            ],
            "Outp": [
               false,
               false,
               false
            ]
         }
      ],
      "IsEnabled": false
   },
   "func (*ProcessState).ExitCode() int": {
      "GeneratedClass": "",
      "GeneratedConditions": "",
      "Blocks": [
         {
            "Inp": [
               false,
               false
            ],
            "Outp": [
               false,
               false
            ]
         }
      ],
      "IsEnabled": false
   },
   "func (*ProcessState).Exited() bool": {
      "GeneratedClass": "",
      "GeneratedConditions": "",
      "Blocks": [
         {
            "Inp": [
               false,
               false
            ],
            "Outp": [
               false,
               false
            ]
         }
      ],
      "IsEnabled": false
   },
   "func (*ProcessState).Pid() int": {
      "GeneratedClass": "",
      "GeneratedConditions": "",
      "Blocks": [
         {
            "Inp": [
               false,
               false
            ],
            "Outp": [
               false,
               false
            ]
         }
      ],
      "IsEnabled": false
   },
   "func (*ProcessState).String() string": {
      "GeneratedClass": "",
      "GeneratedConditions": "",
      "Blocks": [
         {
            "Inp": [
               false,
               false
            ],
            "Outp": [
               false,
               false
            ]
         }
      ],
      "IsEnabled": false
   },
   "func (*ProcessState).Success() bool": {
      "GeneratedClass": "",
      "GeneratedConditions": "",
      "Blocks": [
         {
            "Inp": [
               false,
               false
            ],
            "Outp": [
               false,
               false
            ]
         }
      ],
      "IsEnabled": false
   },
   "func (*ProcessState).Sys() interface{}": {
      "GeneratedClass": "",
      "GeneratedConditions": "",
      "Blocks": [
         {
            "Inp": [
               false,
               false
            ],
            "Outp": [
               false,
               false
            ]
         }
      ],
      "IsEnabled": false
   },
   "func (*ProcessState).SysUsage() interface{}": {
      "GeneratedClass": "",
      "GeneratedConditions": "",
      "Blocks": [
         {
            "Inp": [
               false,
               false
            ],
            "Outp": [
               false,
               false
            ]
         }
      ],
      "IsEnabled": false
   },
   "func (*ProcessState).SystemTime() time.Duration": {
      "GeneratedClass": "",
      "GeneratedConditions": "",
      "Blocks": [
         {
            "Inp": [
               false,
               false
            ],
            "Outp": [
               false,
               false
            ]
         }
      ],
      "IsEnabled": false
   },
   "func (*ProcessState).UserTime() time.Duration": {
      "GeneratedClass": "",
      "GeneratedConditions": "",
      "Blocks": [
         {
            "Inp": [
               false,
               false
            ],
            "Outp": [
               false,
               false
            ]
         }
      ],
      "IsEnabled": false
   },
   "func (*SyscallError).Error() string": {
      "GeneratedClass": "",
      "GeneratedConditions": "",
      "Blocks": [
         {
            "Inp": [
               false,
               false
            ],
            "Outp": [
               false,
               false
            ]
         }
      ],
      "IsEnabled": false
   },
   "func (*SyscallError).Timeout() bool": {
      "GeneratedClass": "",
      "GeneratedConditions": "",
      "Blocks": [
         {
            "Inp": [
               false,
               false
            ],
            "Outp": [
               false,
               false
            ]
         }
      ],
      "IsEnabled": false
   },
   "func (*SyscallError).Unwrap() error": {
      "GeneratedClass": "",
      "GeneratedConditions": "",
      "Blocks": [
         {
            "Inp": [
               false,
               false
            ],
            "Outp": [
               false,
               false
            ]
         }
      ],
      "IsEnabled": false
   },
   "func (FileInfo).IsDir() bool": {
      "GeneratedClass": "",
      "GeneratedConditions": "",
      "Blocks": [
         {
            "Inp": [
               false,
               false
            ],
            "Outp": [
               false,
               false
            ]
         }
      ],
      "IsEnabled": false
   },
   "func (FileInfo).ModTime() time.Time": {
      "GeneratedClass": "",
      "GeneratedConditions": "",
      "Blocks": [
         {
            "Inp": [
               false,
               false
            ],
            "Outp": [
               false,
               false
            ]
         }
      ],
      "IsEnabled": false
   },
   "func (FileInfo).Mode() FileMode": {
      "GeneratedClass": "",
      "GeneratedConditions": "",
      "Blocks": [
         {
            "Inp": [
               false,
               false
            ],
            "Outp": [
               false,
               false
            ]
         }
      ],
      "IsEnabled": false
   },
   "func (FileInfo).Name() string": {
      "GeneratedClass": "",
      "GeneratedConditions": "",
      "Blocks": [
         {
            "Inp": [
               false,
               false
            ],
            "Outp": [
               false,
               false
            ]
         }
      ],
      "IsEnabled": false
   },
   "func (FileInfo).Size() int64": {
      "GeneratedClass": "",
      "GeneratedConditions": "",
      "Blocks": [
         {
            "Inp": [
               false,
               false
            ],
            "Outp": [
               false,
               false
            ]
         }
      ],
      "IsEnabled": false
   },
   "func (FileInfo).Sys() interface{}": {
      "GeneratedClass": "",
      "GeneratedConditions": "",
      "Blocks": [
         {
            "Inp": [
               false,
               false
            ],
            "Outp": [
               false,
               false
            ]
         }
      ],
      "IsEnabled": false
   },
   "func (FileMode).IsDir() bool": {
      "GeneratedClass": "",
      "GeneratedConditions": "",
      "Blocks": [
         {
            "Inp": [
               false,
               false
            ],
            "Outp": [
               false,
               false
            ]
         }
      ],
      "IsEnabled": false
   },
   "func (FileMode).IsRegular() bool": {
      "GeneratedClass": "",
      "GeneratedConditions": "",
      "Blocks": [
         {
            "Inp": [
               false,
               false
            ],
            "Outp": [
               false,
               false
            ]
         }
      ],
      "IsEnabled": false
   },
   "func (FileMode).Perm() FileMode": {
      "GeneratedClass": "",
      "GeneratedConditions": "",
      "Blocks": [
         {
            "Inp": [
               false,
               false
            ],
            "Outp": [
               false,
               false
            ]
         }
      ],
      "IsEnabled": false
   },
   "func (FileMode).String() string": {
      "GeneratedClass": "",
      "GeneratedConditions": "",
      "Blocks": [
         {
            "Inp": [
               false,
               false
            ],
            "Outp": [
               false,
               false
            ]
         }
      ],
      "IsEnabled": false
   },
   "func (Signal).Signal()": {
      "GeneratedClass": "",
      "GeneratedConditions": "",
      "Blocks": [
         {
            "Inp": [
               false
            ],
            "Outp": [
               false
            ]
         }
      ],
      "IsEnabled": false
   },
   "func (Signal).String() string": {
      "GeneratedClass": "",
      "GeneratedConditions": "",
      "Blocks": [
         {
            "Inp": [
               false,
               false
            ],
            "Outp": [
               false,
               false
            ]
         }
      ],
      "IsEnabled": false
   },
   "func Chdir(dir string) error": {
      "GeneratedClass": "",
      "GeneratedConditions": "",
      "Blocks": [
         {
            "Inp": [
               false,
               false
            ],
            "Outp": [
               false,
               false
            ]
         }
      ],
      "IsEnabled": false
   },
   "func Chmod(name string, mode FileMode) error": {
      "GeneratedClass": "",
      "GeneratedConditions": "",
      "Blocks": [
         {
            "Inp": [
               false,
               false,
               false
            ],
            "Outp": [
               false,
               false,
               false
            ]
         }
      ],
      "IsEnabled": false
   },
   "func Chown(name string, uid int, gid int) error": {
      "GeneratedClass": "",
      "GeneratedConditions": "",
      "Blocks": [
         {
            "Inp": [
               false,
               false,
               false,
               false
            ],
            "Outp": [
               false,
               false,
               false,
               false
            ]
         }
      ],
      "IsEnabled": false
   },
   "func Chtimes(name string, atime time.Time, mtime time.Time) error": {
      "GeneratedClass": "",
      "GeneratedConditions": "",
      "Blocks": [
         {
            "Inp": [
               false,
               false,
               false,
               false
            ],
            "Outp": [
               false,
               false,
               false,
               false
            ]
         }
      ],
      "IsEnabled": false
   },
   "func Clearenv()": {
      "GeneratedClass": "",
      "GeneratedConditions": "",
      "Blocks": [
         {
            "Inp": [],
            "Outp": []
         }
      ],
      "IsEnabled": false
   },
   "func Create(name string) (*File, error)": {
      "GeneratedClass": "",
      "GeneratedConditions": "",
      "Blocks": [
         {
            "Inp": [
               false,
               false,
               false
            ],
            "Outp": [
               false,
               false,
               false
            ]
         }
      ],
      "IsEnabled": false
   },
   "func Environ() []string": {
      "GeneratedClass": "",
      "GeneratedConditions": "",
      "Blocks": [
         {
            "Inp": [
               false
            ],
            "Outp": [
               false
            ]
         }
      ],
      "IsEnabled": false
   },
   "func Executable() (string, error)": {
      "GeneratedClass": "",
      "GeneratedConditions": "",
      "Blocks": [
         {
            "Inp": [
               false,
               false
            ],
            "Outp": [
               false,
               false
            ]
         }
      ],
      "IsEnabled": false
   },
   "func Exit(code int)": {
      "GeneratedClass": "",
      "GeneratedConditions": "",
      "Blocks": [
         {
            "Inp": [
               false
            ],
            "Outp": [
               false
            ]
         }
      ],
      "IsEnabled": false
   },
   "func Expand(s string, mapping func(string) string) string": {
      "GeneratedClass": "\n    private class Expand extends TaintTracking::FunctionModel {\n      // signature: func Expand(s string, mapping func(string) string) string\n      Expand() { hasQualifiedName(\"os\", \"Expand\") }\n\n      override predicate hasTaintFlow(FunctionInput inp, FunctionOutput outp) {\n        ((inp.isParameter(0)) and (outp.isResult()))\n      }\n    }",
      "GeneratedConditions": "((inp.isParameter(0)) and (outp.isResult()))",
      "Blocks": [
         {
            "Inp": [
               true,
               false,
               false
            ],
            "Outp": [
               false,
               false,
               true
            ]
         }
      ],
      "IsEnabled": true
   },
   "func ExpandEnv(s string) string": {
      "GeneratedClass": "\n    private class ExpandEnv extends TaintTracking::FunctionModel {\n      // signature: func ExpandEnv(s string) string\n      ExpandEnv() { hasQualifiedName(\"os\", \"ExpandEnv\") }\n\n      override predicate hasTaintFlow(FunctionInput inp, FunctionOutput outp) {\n        ((inp.isParameter(0)) and (outp.isResult()))\n      }\n    }",
      "GeneratedConditions": "((inp.isParameter(0)) and (outp.isResult()))",
      "Blocks": [
         {
            "Inp": [
               true,
               false
            ],
            "Outp": [
               false,
               true
            ]
         }
      ],
      "IsEnabled": true
   },
   "func FindProcess(pid int) (*Process, error)": {
      "GeneratedClass": "",
      "GeneratedConditions": "",
      "Blocks": [
         {
            "Inp": [
               false,
               false,
               false
            ],
            "Outp": [
               false,
               false,
               false
            ]
         }
      ],
      "IsEnabled": false
   },
   "func Getegid() int": {
      "GeneratedClass": "",
      "GeneratedConditions": "",
      "Blocks": [
         {
            "Inp": [
               false
            ],
            "Outp": [
               false
            ]
         }
      ],
      "IsEnabled": false
   },
   "func Getenv(key string) string": {
      "GeneratedClass": "",
      "GeneratedConditions": "",
      "Blocks": [
         {
            "Inp": [
               false,
               false
            ],
            "Outp": [
               false,
               false
            ]
         }
      ],
      "IsEnabled": false
   },
   "func Geteuid() int": {
      "GeneratedClass": "",
      "GeneratedConditions": "",
      "Blocks": [
         {
            "Inp": [
               false
            ],
            "Outp": [
               false
            ]
         }
      ],
      "IsEnabled": false
   },
   "func Getgid() int": {
      "GeneratedClass": "",
      "GeneratedConditions": "",
      "Blocks": [
         {
            "Inp": [
               false
            ],
            "Outp": [
               false
            ]
         }
      ],
      "IsEnabled": false
   },
   "func Getgroups() ([]int, error)": {
      "GeneratedClass": "",
      "GeneratedConditions": "",
      "Blocks": [
         {
            "Inp": [
               false,
               false
            ],
            "Outp": [
               false,
               false
            ]
         }
      ],
      "IsEnabled": false
   },
   "func Getpagesize() int": {
      "GeneratedClass": "",
      "GeneratedConditions": "",
      "Blocks": [
         {
            "Inp": [
               false
            ],
            "Outp": [
               false
            ]
         }
      ],
      "IsEnabled": false
   },
   "func Getpid() int": {
      "GeneratedClass": "",
      "GeneratedConditions": "",
      "Blocks": [
         {
            "Inp": [
               false
            ],
            "Outp": [
               false
            ]
         }
      ],
      "IsEnabled": false
   },
   "func Getppid() int": {
      "GeneratedClass": "",
      "GeneratedConditions": "",
      "Blocks": [
         {
            "Inp": [
               false
            ],
            "Outp": [
               false
            ]
         }
      ],
      "IsEnabled": false
   },
   "func Getuid() int": {
      "GeneratedClass": "",
      "GeneratedConditions": "",
      "Blocks": [
         {
            "Inp": [
               false
            ],
            "Outp": [
               false
            ]
         }
      ],
      "IsEnabled": false
   },
   "func Getwd() (dir string, err error)": {
      "GeneratedClass": "",
      "GeneratedConditions": "",
      "Blocks": [
         {
            "Inp": [
               false,
               false
            ],
            "Outp": [
               false,
               false
            ]
         }
      ],
      "IsEnabled": false
   },
   "func Hostname() (name string, err error)": {
      "GeneratedClass": "",
      "GeneratedConditions": "",
      "Blocks": [
         {
            "Inp": [
               false,
               false
            ],
            "Outp": [
               false,
               false
            ]
         }
      ],
      "IsEnabled": false
   },
   "func IsExist(err error) bool": {
      "GeneratedClass": "",
      "GeneratedConditions": "",
      "Blocks": [
         {
            "Inp": [
               false,
               false
            ],
            "Outp": [
               false,
               false
            ]
         }
      ],
      "IsEnabled": false
   },
   "func IsNotExist(err error) bool": {
      "GeneratedClass": "",
      "GeneratedConditions": "",
      "Blocks": [
         {
            "Inp": [
               false,
               false
            ],
            "Outp": [
               false,
               false
            ]
         }
      ],
      "IsEnabled": false
   },
   "func IsPathSeparator(c uint8) bool": {
      "GeneratedClass": "",
      "GeneratedConditions": "",
      "Blocks": [
         {
            "Inp": [
               false,
               false
            ],
            "Outp": [
               false,
               false
            ]
         }
      ],
      "IsEnabled": false
   },
   "func IsPermission(err error) bool": {
      "GeneratedClass": "",
      "GeneratedConditions": "",
      "Blocks": [
         {
            "Inp": [
               false,
               false
            ],
            "Outp": [
               false,
               false
            ]
         }
      ],
      "IsEnabled": false
   },
   "func IsTimeout(err error) bool": {
      "GeneratedClass": "",
      "GeneratedConditions": "",
      "Blocks": [
         {
            "Inp": [
               false,
               false
            ],
            "Outp": [
               false,
               false
            ]
         }
      ],
      "IsEnabled": false
   },
   "func Lchown(name string, uid int, gid int) error": {
      "GeneratedClass": "",
      "GeneratedConditions": "",
      "Blocks": [
         {
            "Inp": [
               false,
               false,
               false,
               false
            ],
            "Outp": [
               false,
               false,
               false,
               false
            ]
         }
      ],
      "IsEnabled": false
   },
   "func Link(oldname string, newname string) error": {
      "GeneratedClass": "",
      "GeneratedConditions": "",
      "Blocks": [
         {
            "Inp": [
               false,
               false,
               false
            ],
            "Outp": [
               false,
               false,
               false
            ]
         }
      ],
      "IsEnabled": false
   },
   "func LookupEnv(key string) (string, bool)": {
      "GeneratedClass": "",
      "GeneratedConditions": "",
      "Blocks": [
         {
            "Inp": [
               false,
               false,
               false
            ],
            "Outp": [
               false,
               false,
               false
            ]
         }
      ],
      "IsEnabled": false
   },
   "func Lstat(name string) (FileInfo, error)": {
      "GeneratedClass": "",
      "GeneratedConditions": "",
      "Blocks": [
         {
            "Inp": [
               false,
               false,
               false
            ],
            "Outp": [
               false,
               false,
               false
            ]
         }
      ],
      "IsEnabled": false
   },
   "func Mkdir(name string, perm FileMode) error": {
      "GeneratedClass": "",
      "GeneratedConditions": "",
      "Blocks": [
         {
            "Inp": [
               false,
               false,
               false
            ],
            "Outp": [
               false,
               false,
               false
            ]
         }
      ],
      "IsEnabled": false
   },
   "func MkdirAll(path string, perm FileMode) error": {
      "GeneratedClass": "",
      "GeneratedConditions": "",
      "Blocks": [
         {
            "Inp": [
               false,
               false,
               false
            ],
            "Outp": [
               false,
               false,
               false
            ]
         }
      ],
      "IsEnabled": false
   },
   "func NewFile(fd uintptr, name string) *File": {
      "GeneratedClass": "\n    private class NewFile extends TaintTracking::FunctionModel {\n      // signature: func NewFile(fd uintptr, name string) *File\n      NewFile() { hasQualifiedName(\"os\", \"NewFile\") }\n\n      override predicate hasTaintFlow(FunctionInput inp, FunctionOutput outp) {\n        ((inp.isParameter(0)) and (outp.isResult()))\n      }\n    }",
      "GeneratedConditions": "((inp.isParameter(0)) and (outp.isResult()))",
      "Blocks": [
         {
            "Inp": [
               true,
               false,
               false
            ],
            "Outp": [
               false,
               false,
               true
            ]
         }
      ],
      "IsEnabled": true
   },
   "func NewSyscallError(syscall string, err error) error": {
      "GeneratedClass": "",
      "GeneratedConditions": "",
      "Blocks": [
         {
            "Inp": [
               false,
               false,
               false
            ],
            "Outp": [
               false,
               false,
               false
            ]
         }
      ],
      "IsEnabled": false
   },
   "func Open(name string) (*File, error)": {
      "GeneratedClass": "",
      "GeneratedConditions": "",
      "Blocks": [
         {
            "Inp": [
               false,
               false,
               false
            ],
            "Outp": [
               false,
               false,
               false
            ]
         }
      ],
      "IsEnabled": false
   },
   "func OpenFile(name string, flag int, perm FileMode) (*File, error)": {
      "GeneratedClass": "",
      "GeneratedConditions": "",
      "Blocks": [
         {
            "Inp": [
               false,
               false,
               false,
               false,
               false
            ],
            "Outp": [
               false,
               false,
               false,
               false,
               false
            ]
         }
      ],
      "IsEnabled": false
   },
   "func Pipe() (r *File, w *File, err error)": {
      "GeneratedClass": "\n    private class Pipe extends TaintTracking::FunctionModel {\n      // signature: func Pipe() (r *File, w *File, err error)\n      Pipe() { hasQualifiedName(\"os\", \"Pipe\") }\n\n      override predicate hasTaintFlow(FunctionInput inp, FunctionOutput outp) {\n        ((inp.isResult(1)) and (outp.isResult(0)))\n      }\n    }",
      "GeneratedConditions": "((inp.isResult(1)) and (outp.isResult(0)))",
      "Blocks": [
         {
            "Inp": [
               false,
               true,
               false
            ],
            "Outp": [
               true,
               false,
               false
            ]
         }
      ],
      "IsEnabled": true
   },
   "func Readlink(name string) (string, error)": {
      "GeneratedClass": "",
      "GeneratedConditions": "",
      "Blocks": [
         {
            "Inp": [
               false,
               false,
               false
            ],
            "Outp": [
               false,
               false,
               false
            ]
         }
      ],
      "IsEnabled": false
   },
   "func Remove(name string) error": {
      "GeneratedClass": "",
      "GeneratedConditions": "",
      "Blocks": [
         {
            "Inp": [
               false,
               false
            ],
            "Outp": [
               false,
               false
            ]
         }
      ],
      "IsEnabled": false
   },
   "func RemoveAll(path string) error": {
      "GeneratedClass": "",
      "GeneratedConditions": "",
      "Blocks": [
         {
            "Inp": [
               false,
               false
            ],
            "Outp": [
               false,
               false
            ]
         }
      ],
      "IsEnabled": false
   },
   "func Rename(oldpath string, newpath string) error": {
      "GeneratedClass": "",
      "GeneratedConditions": "",
      "Blocks": [
         {
            "Inp": [
               false,
               false,
               false
            ],
            "Outp": [
               false,
               false,
               false
            ]
         }
      ],
      "IsEnabled": false
   },
   "func SameFile(fi1 FileInfo, fi2 FileInfo) bool": {
      "GeneratedClass": "",
      "GeneratedConditions": "",
      "Blocks": [
         {
            "Inp": [
               false,
               false,
               false
            ],
            "Outp": [
               false,
               false,
               false
            ]
         }
      ],
      "IsEnabled": false
   },
   "func Setenv(key string, value string) error": {
      "GeneratedClass": "",
      "GeneratedConditions": "",
      "Blocks": [
         {
            "Inp": [
               false,
               false,
               false
            ],
            "Outp": [
               false,
               false,
               false
            ]
         }
      ],
      "IsEnabled": false
   },
   "func StartProcess(name string, argv []string, attr *ProcAttr) (*Process, error)": {
      "GeneratedClass": "",
      "GeneratedConditions": "",
      "Blocks": [
         {
            "Inp": [
               false,
               false,
               false,
               false,
               false
            ],
            "Outp": [
               false,
               false,
               false,
               false,
               false
            ]
         }
      ],
      "IsEnabled": false
   },
   "func Stat(name string) (FileInfo, error)": {
      "GeneratedClass": "",
      "GeneratedConditions": "",
      "Blocks": [
         {
            "Inp": [
               false,
               false,
               false
            ],
            "Outp": [
               false,
               false,
               false
            ]
         }
      ],
      "IsEnabled": false
   },
   "func Symlink(oldname string, newname string) error": {
      "GeneratedClass": "",
      "GeneratedConditions": "",
      "Blocks": [
         {
            "Inp": [
               false,
               false,
               false
            ],
            "Outp": [
               false,
               false,
               false
            ]
         }
      ],
      "IsEnabled": false
   },
   "func TempDir() string": {
      "GeneratedClass": "",
      "GeneratedConditions": "",
      "Blocks": [
         {
            "Inp": [
               false
            ],
            "Outp": [
               false
            ]
         }
      ],
      "IsEnabled": false
   },
   "func Truncate(name string, size int64) error": {
      "GeneratedClass": "",
      "GeneratedConditions": "",
      "Blocks": [
         {
            "Inp": [
               false,
               false,
               false
            ],
            "Outp": [
               false,
               false,
               false
            ]
         }
      ],
      "IsEnabled": false
   },
   "func Unsetenv(key string) error": {
      "GeneratedClass": "",
      "GeneratedConditions": "",
      "Blocks": [
         {
            "Inp": [
               false,
               false
            ],
            "Outp": [
               false,
               false
            ]
         }
      ],
      "IsEnabled": false
   },
   "func UserCacheDir() (string, error)": {
      "GeneratedClass": "",
      "GeneratedConditions": "",
      "Blocks": [
         {
            "Inp": [
               false,
               false
            ],
            "Outp": [
               false,
               false
            ]
         }
      ],
      "IsEnabled": false
   },
   "func UserConfigDir() (string, error)": {
      "GeneratedClass": "",
      "GeneratedConditions": "",
      "Blocks": [
         {
            "Inp": [
               false,
               false
            ],
            "Outp": [
               false,
               false
            ]
         }
      ],
      "IsEnabled": false
   },
   "func UserHomeDir() (string, error)": {
      "GeneratedClass": "",
      "GeneratedConditions": "",
      "Blocks": [
         {
            "Inp": [
               false,
               false
            ],
            "Outp": [
               false,
               false
            ]
         }
      ],
      "IsEnabled": false
   }
}
